{"total":36,"pageSize":10,"pageCount":4,"data":[{"title":"【译】React 中 State, Store, Static, This 的几个问题","slug":"react-state-this-static-store","date":"2018-10-31T14:40:13.000Z","updated":"2019-04-23T15:49:06.000Z","comments":true,"path":"api/articles/react-state-this-static-store.json","excerpt":null,"keywords":null,"cover":null,"content":null,"raw":null,"categories":[{"name":"前端技术","path":"api/categories/前端技术.json"}],"tags":[{"name":"Front-End","path":"api/tags/Front-End.json"},{"name":"React","path":"api/tags/React.json"}]},{"title":"代码的艺术 - 章淼讲座笔记","slug":"Art-Of-Code","date":"2018-10-08T02:41:48.000Z","updated":"2018-10-08T02:04:33.000Z","comments":true,"path":"api/articles/Art-Of-Code.json","excerpt":null,"keywords":null,"cover":null,"content":null,"raw":null,"categories":[],"tags":[{"name":"总结","path":"api/tags/总结.json"}]},{"title":"VSCode 插件开发急速入门","slug":"vscode-extands-step-0","date":"2018-06-13T07:41:48.000Z","updated":"2018-06-16T03:26:44.000Z","comments":true,"path":"api/articles/vscode-extands-step-0.json","excerpt":null,"keywords":null,"cover":"https://img30.360buyimg.com/uba/jfs/t20848/320/1132999703/64245/a47741fc/5b20d75eN83303d8b.png","content":null,"raw":null,"categories":[],"tags":[{"name":"Front-End","path":"api/tags/Front-End.json"},{"name":"Tool","path":"api/tags/Tool.json"},{"name":"NodeJS","path":"api/tags/NodeJS.json"}]},{"title":"Webpack 4 实战 React 和 Vue 项目","slug":"something-about-webpack-4","date":"2018-06-11T09:48:23.000Z","updated":"2018-06-20T01:31:47.000Z","comments":true,"path":"api/articles/something-about-webpack-4.json","excerpt":null,"keywords":null,"cover":null,"content":null,"raw":null,"categories":[{"name":"前端技术","path":"api/categories/前端技术.json"}],"tags":[{"name":"Webpack","path":"api/tags/Webpack.json"},{"name":"React","path":"api/tags/React.json"},{"name":"Vue","path":"api/tags/Vue.json"}]},{"title":"【译】Google 出品 - 利用 webpack 做 web 性能优化","slug":"blog-translate-web-performance-optimization-with-webpack-from-google-webpack4","date":"2018-05-02T06:35:33.000Z","updated":"2018-06-20T01:31:47.000Z","comments":true,"path":"api/articles/blog-translate-web-performance-optimization-with-webpack-from-google-webpack4.json","excerpt":null,"keywords":null,"cover":"https://img20.360buyimg.com/uba/jfs/t15217/149/2229580840/12989/54324b99/5a815957N5bb3e0c6.png","content":null,"raw":null,"categories":[{"name":"前端技术","path":"api/categories/前端技术.json"}],"tags":[{"name":"翻译","path":"api/tags/翻译.json"},{"name":"Webpack","path":"api/tags/Webpack.json"}]},{"title":"【译】Webpack 4 mode and optimization","slug":"blog-translate-webpack-4-mode-and-optimization","date":"2018-04-18T06:26:11.000Z","updated":"2018-06-20T01:31:47.000Z","comments":true,"path":"api/articles/blog-translate-webpack-4-mode-and-optimization.json","excerpt":null,"keywords":null,"cover":"https://img14.360buyimg.com/uba/s750x500_jfs/t17446/171/1782320374/354853/1568df4e/5ad6eac5Na2c1d8ee.jpg!cc_2x1","content":null,"raw":null,"categories":[{"name":"前端技术","path":"api/categories/前端技术.json"}],"tags":[{"name":"Webpack","path":"api/tags/Webpack.json"},{"name":"构建工具","path":"api/tags/构建工具.json"}]},{"title":"移动端 HTTPS 抓包工具配置说明","slug":"mobile-https-config","date":"2018-03-29T10:53:55.000Z","updated":"2018-06-20T01:31:47.000Z","comments":true,"path":"api/articles/mobile-https-config.json","excerpt":null,"keywords":null,"cover":"https://img20.360buyimg.com/uba/jfs/t16375/210/2520307643/222582/31ac0971/5ab0a175N3cbadb49.png.webp","content":null,"raw":null,"categories":[{"name":"前端技术","path":"api/categories/前端技术.json"}],"tags":[{"name":"移动开发","path":"api/tags/移动开发.json"}]},{"title":"iOS HTTPS 抓包工具配置说明","slug":"iOS-https","date":"2018-03-01T10:53:55.000Z","updated":"2018-06-20T01:31:47.000Z","comments":true,"path":"api/articles/iOS-https.json","excerpt":null,"keywords":null,"cover":"https://img20.360buyimg.com/uba/jfs/t16375/210/2520307643/222582/31ac0971/5ab0a175N3cbadb49.png.webp","content":null,"raw":null,"categories":[{"name":"前端技术","path":"api/categories/前端技术.json"}],"tags":[{"name":"移动开发","path":"api/tags/移动开发.json"}]},{"title":"【译】利用 webpack 做 web 性能优化","slug":"blog-translate-web-performance-optimization-with-webpack-from-google","date":"2018-02-11T06:35:33.000Z","updated":"2018-06-20T01:31:47.000Z","comments":true,"path":"api/articles/blog-translate-web-performance-optimization-with-webpack-from-google.json","excerpt":null,"keywords":null,"cover":"https://img20.360buyimg.com/uba/jfs/t15217/149/2229580840/12989/54324b99/5a815957N5bb3e0c6.png","content":null,"raw":null,"categories":[{"name":"前端技术","path":"api/categories/前端技术.json"}],"tags":[{"name":"翻译","path":"api/tags/翻译.json"},{"name":"Webpack","path":"api/tags/Webpack.json"}]},{"title":"【译】NPM vs Bower vs Browserify vs Gulp vs Grunt vs Webpack","slug":"NPM-vs-Bower-vs-Browserify-vs-Gulp-vs-Grunt-vs-Webpack","date":"2016-06-17T06:35:33.000Z","updated":"2018-06-20T01:31:47.000Z","comments":true,"path":"api/articles/NPM-vs-Bower-vs-Browserify-vs-Gulp-vs-Grunt-vs-Webpack.json","excerpt":null,"keywords":null,"cover":null,"content":null,"raw":null,"categories":[{"name":"前端技术","path":"api/categories/前端技术.json"}],"tags":[{"name":"翻译","path":"api/tags/翻译.json"},{"name":"Webpack","path":"api/tags/Webpack.json"},{"name":"NPM","path":"api/tags/NPM.json"}]}]}