{"name":"阅读","postlist":[{"title":"英雄再见","slug":"2013-12-04-Finished-the-book","date":"2013-12-03T16:00:01.000Z","updated":"2018-02-27T04:13:00.371Z","comments":true,"path":"api/articles/2013-12-04-Finished-the-book.json","excerpt":null,"keywords":null,"cover":null,"content":null,"raw":null,"categories":[{"name":"blog","path":"api/categories/blog.json"}],"tags":[{"name":"阅读","path":"api/tags/阅读.json"}]},{"title":"书摘随笔","slug":"2014-03-20-Read-The-Book-Of-Zhihu","date":"2014-03-19T16:00:01.000Z","updated":"2018-02-27T04:13:34.164Z","comments":true,"path":"api/articles/2014-03-20-Read-The-Book-Of-Zhihu.json","excerpt":null,"keywords":null,"cover":null,"content":null,"raw":null,"categories":[{"name":"blog","path":"api/categories/blog.json"}],"tags":[{"name":"阅读","path":"api/tags/阅读.json"}]}]}